README.rst
setup.py
slacker2/__init__.py
slacker2/base_api.py
slacker2/chat.py
slacker2/constants.py
slacker2/utilities.py
slacker2.egg-info/PKG-INFO
slacker2.egg-info/SOURCES.txt
slacker2.egg-info/dependency_links.txt
slacker2.egg-info/requires.txt
slacker2.egg-info/top_level.txt