Metadata-Version: 2.1
Name: slacker2
Version: 22.8.4
Summary: Slack API client, fork of slacker
Home-page: http://github.com/senpay/slacker/
Author: Oktay Sancak, Alexander Pushkarev
Author-email: oktaysancak@gmail.com, alexspush@gmail.com
License: http://www.apache.org/licenses/LICENSE-2.0
Keywords: slack api
Platform: UNKNOWN
Classifier: Intended Audience :: Developers
Classifier: License :: OSI Approved :: Apache Software License
Classifier: Natural Language :: English
Classifier: Programming Language :: Python
Classifier: Programming Language :: Python :: 3
Classifier: Programming Language :: Python :: 3.5
Classifier: Programming Language :: Python :: 3.6
Classifier: Programming Language :: Python :: 3.7
Classifier: Programming Language :: Python :: 3.8
